mlgym_ollama_llm/__init__.py
mlgym_ollama_llm/llm.py
mlgym_ollama_llm-0.3.0.dist-info/licenses/LICENSE
mlgym_ollama_llm-0.3.0.dist-info/METADATA
mlgym_ollama_llm-0.3.0.dist-info/WHEEL
mlgym_ollama_llm-0.3.0.dist-info/top_level.txt
mlgym_ollama_llm-0.3.0.dist-info/RECORD
