Metadata-Version: 2.4
Name: mlgym_ollama_llm
Version: 0.3.0
Summary: A custom MLGym Ollama wrapper for seamless interactions with LlamaIndex LLMs. This wrapper enables smooth interactions with the Ollama API by automatically including necessary HTTP headers.
Author: Stratus5
Author-email: operations@stratus5.com
Classifier: Programming Language :: Python :: 3
Classifier: License :: OSI Approved :: MIT License
License-File: LICENSE
Requires-Dist: llama-index>=0.14.8
Requires-Dist: ollama>=0.6.1
Dynamic: author
Dynamic: author-email
Dynamic: classifier
Dynamic: description-content-type
Dynamic: license-file
Dynamic: requires-dist
Dynamic: summary
